cloudbase_agent/__init__.py
cloudbase_agent/llama_index/agent.py
cloudbase_agent/llama_index/workflow.py
cloudbase_agent_llama_index-0.1.11.dist-info/METADATA
cloudbase_agent_llama_index-0.1.11.dist-info/WHEEL
cloudbase_agent_llama_index-0.1.11.dist-info/RECORD
